bin/combinetf2_fit.py
bin/combinetf2_plot_hists.py
bin/combinetf2_plot_hists_cov.py
bin/combinetf2_plot_hists_uncertainties.py
bin/combinetf2_plot_inputdata.py
bin/combinetf2_plot_likelihood_scan.py
bin/combinetf2_plot_likelihood_scan2D.py
bin/combinetf2_plot_pulls_and_impacts.py
bin/combinetf2_print_impacts.py
bin/combinetf2_print_pulls_and_constraints.py
bin/debug_inputdata.py
bin/text2hdf5.py
combinetf2/__init__.py
combinetf2/common.py
combinetf2/datacard_converter.py
combinetf2/datacard_parser.py
combinetf2/debugdata.py
combinetf2/fitter.py
combinetf2/h5pyutils.py
combinetf2/inputdata.py
combinetf2/io_tools.py
combinetf2/scipyhelpers.py
combinetf2/tensorwriter.py
combinetf2/tfhelpers.py
combinetf2/workspace.py
combinetf2/physicsmodels/__init__.py
combinetf2/physicsmodels/angular_coefficients.py
combinetf2/physicsmodels/helpers.py
combinetf2/physicsmodels/physicsmodel.py
combinetf2/physicsmodels/project.py
combinetf2/physicsmodels/ratio.py
tests/__init__.py
tests/make_tensor.py
tests/param_model.py
tests/style_config.py
combinetf2-0.2.0.dist-info/METADATA
combinetf2-0.2.0.dist-info/WHEEL
combinetf2-0.2.0.dist-info/entry_points.txt
combinetf2-0.2.0.dist-info/top_level.txt
combinetf2-0.2.0.dist-info/RECORD
