Metadata-Version: 2.4
Name: combinetf2
Version: 0.2.0
Summary: .
Author-email: David Walter <david.walter@cern.ch>, Josh Bendavid <josh.bendavid@cern.ch>, Kenneth Long <kenneth.long@cern.ch>
License: MIT
Project-URL: Homepage, https://github.com/WMass/combinetf2
Classifier: Programming Language :: Python :: 3
Classifier: Programming Language :: Python :: 3.8
Classifier: License :: OSI Approved :: MIT License
Classifier: Operating System :: OS Independent
Requires-Python: >=3.8
Requires-Dist: tensorflow
Requires-Dist: tensorflow-probability
Requires-Dist: wums
Requires-Dist: numpy
Requires-Dist: h5py
Requires-Dist: hist
Requires-Dist: scipy
Provides-Extra: plotting
Requires-Dist: matplotlib; extra == "plotting"
Requires-Dist: mplhep; extra == "plotting"
Requires-Dist: seaborn; extra == "plotting"
Requires-Dist: pandas; extra == "plotting"
Requires-Dist: plotly; extra == "plotting"
Requires-Dist: kaleido; extra == "plotting"
Provides-Extra: convsersion
Requires-Dist: uproot; extra == "convsersion"
Provides-Extra: all
Requires-Dist: plotting; extra == "all"
Requires-Dist: convsersion; extra == "all"
